{
    "start_user": "Вас приветствует официальный бот Переправы Салехард - Лабытнанги. Выберите необходимый пункт \"Меню\" или отправьте  команду /menu всли меню не отобразилось:",
    "start_moderator": "Вас приветствует официальный бот Переправы Салехард - Лабытнанги. Выберите необходимый пункт \"Меню\" или отправьте  команду /menu всли меню не отобразилось:",
    "menu_user": "Приветствую, {user_name}, выберите необходимый пункт \"Меню\" или отправьте  команду /menu всли меню не отобразилось:",
    
    "menu_manager": "Приветствую, %Модератор%, ",
    "message_types": "Выберите тип сообщения:",
    "choose_crossings": "Выберите переправы, которые вы хотите отправить сообщение:",
    "appeal_message": "Введите текст вашего обращения.",
    "appeal_message_success": "Ваше обращение принято.",
    "appeal_message_already_answered": "Обращение уже отвечено.",
    "appeal_message_answered": "Обращение отвечено."
}
